yasmot/__init__.py
yasmot/definitions.py
yasmot/frames.py
yasmot/main.py
yasmot/parser.py
yasmot/tracking.py
yasmot-0.10.dist-info/METADATA
yasmot-0.10.dist-info/WHEEL
yasmot-0.10.dist-info/entry_points.txt
yasmot-0.10.dist-info/top_level.txt
yasmot-0.10.dist-info/RECORD
