Metadata-Version: 2.4
Name: yasmot
Version: 0.10
Summary: Object tracker for stereo images and video
Author: Ketil Malde
Author-email: ketil@malde.org
License: LGPL
Keywords: object tracking
Classifier: Programming Language :: Python :: 3
Classifier: Development Status :: 4 - Beta
Classifier: Environment :: Console
Requires-Python: >=3.8
Requires-Dist: parse
Requires-Dist: scipy
